{
   "volume": "53",
   "character":"traditional",
   "table_of_content": [
       {
           "category": "刊首語",
           "articles": [
               {
                   "title": "心靈禱告",
                   "author": "編輯同工組",
                   "id": "0_prayer_t"
               }
           ]
       }
       ,
       {
           "category": "主題分享",
           "articles": [
               {
                   "title": "The Salvation of Christ",
                   "author": "Rev. Werner Peters",
                   "id": "The Salvation of Christ"
               }
               ,
               {
                   "title": "基 督 的 救 恩",
                   "author": "畢維耐 牧師 （Werner Peters）",
                   "id": "2_bwn_t"
               }
           ]
       }
       ,
       {
           "category": "培灵讲座",
           "articles": [
               {
                   "title": "認識神（十二）：謹慎管理神的家",
                   "author": "保羅•華許",
                   "id": "3_paulwasher_t"
               }
           ]
       }
       ,
       {
           "category": "宣教專題",
           "articles": [
               {
                   "title": "計劃前赴 甘願留下",
                   "author": "喬治莫瑞 博士（Dr.George Murray）",
                   "id": "4_george_t"
               }
           ]
       }
       ,
       {
           "category": "得救見證",
           "articles": [
               {
                   "title": "原來，信很簡單，就是“順服”",
                   "author": "漆洳言",
                   "id": "5_qry_t"
               }
			   ,
               {
                   "title": "神至終帶我歸向耶穌",
                   "author": "殷群",
                   "id": "6_yq_t"
               }
           ]
       }
       ,
       {
           "category": "生命歷程",
           "articles": [
               {
                   "title": "神呼召我全職服侍",
                   "author": "Lucy",
                   "id": "7_lucy_t"
               }
               ,
               {
                   "title": "三個奇妙的收獲",
                   "author": "Steven",
                   "id": "8_steven_t"
               }
           ]
       }
       ,
       {
           "category": "信仰生活",
           "articles": [
               {
                   "title": "感恩相聚",
                   "author": "Huang45",
                   "id": "9_huang45_t"
               }
           ]
       }
       ,
       {
           "category": "历史纵览",
           "articles": [
               {
                   "title": "當上帝的話語直接照耀——紀念宗教改革500周年",
                   "author": "嚴行",
                   "id": "10_yx_t"
               }
           ]
       }
       ,
       {
           "category": "电影评论",
           "articles": [
               {
                   "title": "滿身泥濘，取水得潔淨——電影《驢得水》觀後感",
                   "author": "謝恩音",
                   "id": "11_xey_t"
               }
           ]
       }
       ,
       {
           "category": "经文释义",
           "articles": [
               {
                   "title": "重 生 真 義——約翰福音講解（九）",
                   "author": "馮津 牧師",
                   "id": "12_fj_t"
               }
           ]
       }
	   ,
       {
           "category": "一问一答",
           "articles": [
               {
                   "title": "為何說耶穌是唯一的救主？",
                   "author": "蒙恩",
                   "id": "13_qa_t"
               }
           ]
       }
       ,
       {
           "category": "",
           "articles": [
               {
                   "title": "《溪水旁》2017年約稿信",
                   "author": "溪水旁編輯組",
                   "id": "14_2017 yue gao xing_t"
               }
           ]
       }
   ]
}
